franklin_container/__init__.py
franklin_container/magic.py
franklin_container-0.1.6.dist-info/licenses/LICENSE
franklin_container-0.1.6.dist-info/METADATA
franklin_container-0.1.6.dist-info/WHEEL
franklin_container-0.1.6.dist-info/entry_points.txt
franklin_container-0.1.6.dist-info/top_level.txt
franklin_container-0.1.6.dist-info/RECORD
