Metadata-Version: 2.4
Name: franklin_container
Version: 0.1.6
Summary: Terminal client for Jupyter exercises
Author-email: Kasper Munch <kaspermunch@birc.au.dk>
Maintainer-email: Kasper Munch <kaspermunch@birc.au.dk>
Project-URL: Homepage, https://github.com/yourusername/franklin_container
Keywords: teaching,data,jupyter,docker,git
Classifier: Development Status :: 4 - Beta
Classifier: Intended Audience :: Education
Classifier: Topic :: Software Development :: Build Tools
Classifier: Programming Language :: Python :: 3
Classifier: Programming Language :: Python :: 3.9
Classifier: Programming Language :: Python :: 3.10
Classifier: Programming Language :: Python :: 3.11
Classifier: Programming Language :: Python :: 3.12
Classifier: Programming Language :: Python :: 3.13
Requires-Python: >=3.9
License-File: LICENSE
Requires-Dist: jupyterlab>=4
Requires-Dist: ipython
Requires-Dist: pyperclip
Dynamic: license-file
